{
  "code": "qa-shitsugi-sozoku",
  "type": "qa",
  "count": 129,
  "articles": [
    {
      "id": "01-01",
      "title": "民法第255条の規定により共有持分を取得した場合の相続税の課税関係",
      "cite_key": "質疑応答01-01",
      "tax_type": "sozoku",
      "size": 2084
    },
    {
      "id": "01-02",
      "title": "家附の継子と相続税法第15条第2項の相続人",
      "cite_key": "質疑応答01-02",
      "tax_type": "sozoku",
      "size": 2022
    },
    {
      "id": "02-01",
      "title": "被相続人の準確定申告に係る還付金等",
      "cite_key": "質疑応答02-01",
      "tax_type": "sozoku",
      "size": 2178
    },
    {
      "id": "02-02",
      "title": "所有権留保契約に基づいて割賦購入された住宅を相続により取得した場合",
      "cite_key": "質疑応答02-02",
      "tax_type": "sozoku",
      "size": 2173
    },
    {
      "id": "02-03",
      "title": "支払期日未到来の既経過家賃と相続財産",
      "cite_key": "質疑応答02-03",
      "tax_type": "sozoku",
      "size": 1704
    },
    {
      "id": "02-04",
      "title": "確定申告書提出後に死亡した被相続人に係る還付加算金の課税関係",
      "cite_key": "質疑応答02-04",
      "tax_type": "sozoku",
      "size": 1897
    },
    {
      "id": "02-05",
      "title": "財団たる医療法人に対する残余財産分配請求権の相続性",
      "cite_key": "質疑応答02-05",
      "tax_type": "sozoku",
      "size": 2034
    },
    {
      "id": "02-06",
      "title": "連生終身保険における高度障害保険金等の課税関係",
      "cite_key": "質疑応答02-06",
      "tax_type": "sozoku",
      "size": 2936
    },
    {
      "id": "02-07",
      "title": "ハワイ州に所在するコンドミニアムの合有不動産権を相続税の課税対象とすることの可否",
      "cite_key": "質疑応答02-07",
      "tax_type": "sozoku",
      "size": 3999
    },
    {
      "id": "02-09",
      "title": "未支給の国民年金に係る相続税の課税関係",
      "cite_key": "質疑応答02-09",
      "tax_type": "sozoku",
      "size": 4265
    },
    {
      "id": "02-10",
      "title": "国家公務員の殉職によりその遺族に授与された賞じゅつ金の課税関係",
      "cite_key": "質疑応答02-10",
      "tax_type": "sozoku",
      "size": 5673
    },
    {
      "id": "02-11",
      "title": "相互会社が株式会社に組織変更した場合の相続税の取扱い",
      "cite_key": "質疑応答02-11",
      "tax_type": "sozoku",
      "size": 9345
    },
    {
      "id": "02-12",
      "title": "相続開始時点で売買契約中であった不動産に係る相続税の課税",
      "cite_key": "質疑応答02-12",
      "tax_type": "sozoku",
      "size": 4822
    },
    {
      "id": "03-01",
      "title": "特別夫婦年金保険に係る課税関係",
      "cite_key": "質疑応答03-01",
      "tax_type": "sozoku",
      "size": 4586
    },
    {
      "id": "03-02",
      "title": "人身傷害補償保険の後遺障害保険金を定期金により受け取っていた者が死亡した場合に支払われる一時金",
      "cite_key": "質疑応答03-02",
      "tax_type": "sozoku",
      "size": 2853
    },
    {
      "id": "03-05",
      "title": "建物更生共済契約に係る課税関係",
      "cite_key": "質疑応答03-05",
      "tax_type": "sozoku",
      "size": 1956
    },
    {
      "id": "03-06",
      "title": "生前に退職している被相続人の死亡により元の勤務先から支払いを受ける特別弔慰金等",
      "cite_key": "質疑応答03-06",
      "tax_type": "sozoku",
      "size": 2419
    },
    {
      "id": "03-07",
      "title": "被相続人の死亡退職に伴い遺族補償金として支給された金額",
      "cite_key": "質疑応答03-07",
      "tax_type": "sozoku",
      "size": 1903
    },
    {
      "id": "03-08",
      "title": "失踪宣告が行われたことに伴い死亡退職金の支払いがあった場合の課税関係",
      "cite_key": "質疑応答03-08",
      "tax_type": "sozoku",
      "size": 3348
    },
    {
      "id": "03-09",
      "title": "死亡退職金の課税時期",
      "cite_key": "質疑応答03-09",
      "tax_type": "sozoku",
      "size": 1898
    },
    {
      "id": "03-10",
      "title": "死亡退職金を辞退した場合",
      "cite_key": "質疑応答03-10",
      "tax_type": "sozoku",
      "size": 1903
    },
    {
      "id": "03-11",
      "title": "遺言に基づき遺産の換価代金で特定公益信託を設定した場合の相続税及び譲渡所得の課税関係",
      "cite_key": "質疑応答03-11",
      "tax_type": "sozoku",
      "size": 5055
    },
    {
      "id": "04-01",
      "title": "町内会に寄附した相続財産",
      "cite_key": "質疑応答04-01",
      "tax_type": "sozoku",
      "size": 1563
    },
    {
      "id": "04-02",
      "title": "庭内神しの敷地等",
      "cite_key": "質疑応答04-02",
      "tax_type": "sozoku",
      "size": 2290
    },
    {
      "id": "05-01",
      "title": "加害者が死亡した場合における損害賠償金についての債務控除",
      "cite_key": "質疑応答05-01",
      "tax_type": "sozoku",
      "size": 1816
    },
    {
      "id": "05-02",
      "title": "被相続人が雇用していた従業員を相続開始後に解雇し退職金を支払った場合の債務控除",
      "cite_key": "質疑応答05-02",
      "tax_type": "sozoku",
      "size": 1922
    },
    {
      "id": "05-03",
      "title": "合名会社等の無限責任社員の会社債務についての債務控除の適用",
      "cite_key": "質疑応答05-03",
      "tax_type": "sozoku",
      "size": 1961
    },
    {
      "id": "05-04",
      "title": "限定承認をした後に退職手当金が支給された場合の債務控除",
      "cite_key": "質疑応答05-04",
      "tax_type": "sozoku",
      "size": 1637
    },
    {
      "id": "06-01",
      "title": "外国人である被相続人の日本人妻と相続税法第15条第2項に規定する法定相続人",
      "cite_key": "質疑応答06-01",
      "tax_type": "sozoku",
      "size": 1788
    },
    {
      "id": "06-02",
      "title": "代襲相続権の有無（1）",
      "cite_key": "質疑応答06-02",
      "tax_type": "sozoku",
      "size": 1128
    },
    {
      "id": "06-03",
      "title": "相続税法第15条第3項の規定により実子とみなされる養子の範囲",
      "cite_key": "質疑応答06-03",
      "tax_type": "sozoku",
      "size": 2271
    },
    {
      "id": "06-04",
      "title": "養子縁組前に出生した養子の子の代襲相続権の有無",
      "cite_key": "質疑応答06-04",
      "tax_type": "sozoku",
      "size": 1407
    },
    {
      "id": "06-05",
      "title": "代襲相続権の有無（2）",
      "cite_key": "質疑応答06-05",
      "tax_type": "sozoku",
      "size": 1371
    },
    {
      "id": "06-06",
      "title": "代襲相続権の有無（3）",
      "cite_key": "質疑応答06-06",
      "tax_type": "sozoku",
      "size": 1537
    },
    {
      "id": "07-01",
      "title": "相続を放棄した代襲相続人に遺贈財産がある場合の相続税の2割加算",
      "cite_key": "質疑応答07-01",
      "tax_type": "sozoku",
      "size": 1693
    },
    {
      "id": "07-02",
      "title": "相続税法第18条の解釈",
      "cite_key": "質疑応答07-02",
      "tax_type": "sozoku",
      "size": 2027
    },
    {
      "id": "07-03",
      "title": "被相続人の直系卑属でない者が養子となっている場合の相続税の2割加算",
      "cite_key": "質疑応答07-03",
      "tax_type": "sozoku",
      "size": 1351
    },
    {
      "id": "07-04",
      "title": "被相続人の直系卑属である者が養子となっている場合の相続税の2割加算",
      "cite_key": "質疑応答07-04",
      "tax_type": "sozoku",
      "size": 1804
    },
    {
      "id": "08-01",
      "title": "無制限納税義務者に係る未成年者控除の控除不足額を制限納税義務者である未成年者から控除することの可否",
      "cite_key": "質疑応答08-01",
      "tax_type": "sozoku",
      "size": 2539
    },
    {
      "id": "08-03",
      "title": "配偶者に対する相続税額の軽減の規定の適用を受ける場合の「相続分不存在証明書」の適否",
      "cite_key": "質疑応答08-03",
      "tax_type": "sozoku",
      "size": 2837
    },
    {
      "id": "08-04",
      "title": "米国籍を有する納税義務者が相続税の申告書に添付する印鑑証明書",
      "cite_key": "質疑応答08-04",
      "tax_type": "sozoku",
      "size": 2087
    },
    {
      "id": "08-05",
      "title": "隠蔽又は仮装に係る財産があった場合の配偶者に対する相続税額の軽減",
      "cite_key": "質疑応答08-05",
      "tax_type": "sozoku",
      "size": 3310
    },
    {
      "id": "09-01",
      "title": "変額年金保険契約に基づく年金に関する権利の評価",
      "cite_key": "質疑応答09-01",
      "tax_type": "sozoku",
      "size": 2137
    },
    {
      "id": "09-02",
      "title": "年金支給による退職金の評価及び遺族年金",
      "cite_key": "質疑応答09-02",
      "tax_type": "sozoku",
      "size": 2351
    },
    {
      "id": "10-01",
      "title": "相続開始の年に被相続人から贈与を受けた宅地に係る小規模宅地等の特例の適用の可否",
      "cite_key": "質疑応答10-01",
      "tax_type": "sozoku",
      "size": 2582
    },
    {
      "id": "10-02",
      "title": "小規模宅地等の特例の対象となる私道",
      "cite_key": "質疑応答10-02",
      "tax_type": "sozoku",
      "size": 1679
    },
    {
      "id": "10-03",
      "title": "共有家屋(貸家)の敷地の用に供されていた宅地等についての小規模宅地等の特例の選択",
      "cite_key": "質疑応答10-03",
      "tax_type": "sozoku",
      "size": 2153
    },
    {
      "id": "10-04",
      "title": "遺留分減殺に伴う修正申告及び更正の請求における小規模宅地等の選択替えの可否（令和元年7月1日前に開始した相続）",
      "cite_key": "質疑応答10-04",
      "tax_type": "sozoku",
      "size": 3093
    },
    {
      "id": "10-05",
      "title": "小規模宅地等の特例の対象となる「被相続人等の居住の用に供されていた宅地等」の判定",
      "cite_key": "質疑応答10-05",
      "tax_type": "sozoku",
      "size": 2398
    },
    {
      "id": "10-06",
      "title": "入院により空家となっていた建物の敷地についての小規模宅地等の特例",
      "cite_key": "質疑応答10-06",
      "tax_type": "sozoku",
      "size": 2131
    },
    {
      "id": "10-08",
      "title": "特定居住用宅地等の要件の一つである「相続開始時から申告期限まで引き続き当該建物に居住していること」の意義",
      "cite_key": "質疑応答10-08",
      "tax_type": "sozoku",
      "size": 2561
    },
    {
      "id": "10-09",
      "title": "特定同族会社に貸し付けられていた建物が相続税の申告期限までに建て替えられた場合の小規模宅地等の特例",
      "cite_key": "質疑応答10-09",
      "tax_type": "sozoku",
      "size": 2537
    },
    {
      "id": "10-10",
      "title": "小規模宅地等の特例の適用を受けることができる者の範囲(人格のない社団)",
      "cite_key": "質疑応答10-10",
      "tax_type": "sozoku",
      "size": 1642
    },
    {
      "id": "10-11",
      "title": "小規模宅地等の特例の対象となる宅地等の範囲(財産管理人の事業)",
      "cite_key": "質疑応答10-11",
      "tax_type": "sozoku",
      "size": 1950
    },
    {
      "id": "10-12",
      "title": "被相続人の共有する土地が被相続人等の居住の用と貸家の敷地の用に供されていた場合の小規模宅地等の特例",
      "cite_key": "質疑応答10-12",
      "tax_type": "sozoku",
      "size": 2222
    },
    {
      "id": "10-14",
      "title": "単身赴任中の相続人が取得した被相続人の居住用宅地等についての小規模宅地等の特例",
      "cite_key": "質疑応答10-14",
      "tax_type": "sozoku",
      "size": 2436
    },
    {
      "id": "10-15",
      "title": "老人ホームへの入所により空家となっていた建物の敷地についての小規模宅地等の特例（平成26年1月1日以後に相続又は遺贈により取得する場合の取扱い）",
      "cite_key": "質疑応答10-15",
      "tax_type": "sozoku",
      "size": 4171
    },
    {
      "id": "10-16",
      "title": "老人ホームに入所していた被相続人が要介護認定の申請中に死亡した場合の小規模宅地等の特例",
      "cite_key": "質疑応答10-16",
      "tax_type": "sozoku",
      "size": 4304
    },
    {
      "id": "10-17",
      "title": "遺留分侵害額の請求に伴い取得した宅地に係る小規模宅地等の特例の適用の可否（令和元年7月1日以後に開始した相続）",
      "cite_key": "質疑応答10-17",
      "tax_type": "sozoku",
      "size": 4193
    },
    {
      "id": "10-18",
      "title": "法人所有建物の建替え中に相続開始した場合の小規模宅地の特例の適用",
      "cite_key": "質疑応答10-18",
      "tax_type": "sozoku",
      "size": 2805
    },
    {
      "id": "11-01",
      "title": "認定死亡と相続開始があったことを知った日",
      "cite_key": "質疑応答11-01",
      "tax_type": "sozoku",
      "size": 1827
    },
    {
      "id": "11-02",
      "title": "被相続人が外国人である場合の未分割遺産に対する課税",
      "cite_key": "質疑応答11-02",
      "tax_type": "sozoku",
      "size": 1740
    },
    {
      "id": "11-03",
      "title": "共同相続人の1人が遺産分割の調停において相続財産を取得しないことが確定した場合の相続税法第32条第1項の規定に基づく更正の請求",
      "cite_key": "質疑応答11-03",
      "tax_type": "sozoku",
      "size": 2632
    },
    {
      "id": "11-04",
      "title": "暦年課税の適用を受けた贈与財産について評価誤りが判明した場合の相続税の課税価格に加算される財産の価額",
      "cite_key": "質疑応答11-04",
      "tax_type": "sozoku",
      "size": 3383
    },
    {
      "id": "12-01",
      "title": "相続財産の寄附を受けた公益法人が当該財産の売却代金を法人の事業の用に供した場合",
      "cite_key": "質疑応答12-01",
      "tax_type": "sozoku",
      "size": 2406
    },
    {
      "id": "12-02",
      "title": "相続開始後に相続財産である山林について宅地開発を行い道路部分を市に贈与した場合の租税特別措置法第70条の適用",
      "cite_key": "質疑応答12-02",
      "tax_type": "sozoku",
      "size": 2214
    },
    {
      "id": "13-01",
      "title": "遺産の換価分割のための相続登記と贈与税",
      "cite_key": "質疑応答13-01",
      "tax_type": "sozoku",
      "size": 1558
    },
    {
      "id": "14-01",
      "title": "社会保険診療報酬の所得計算の特例の適用を受けた青色申告事業主が配偶者に支給した専従者給与と贈与税",
      "cite_key": "質疑応答14-01",
      "tax_type": "sozoku",
      "size": 2397
    },
    {
      "id": "14-02",
      "title": "使用貸借に係る農地の離作料と贈与税",
      "cite_key": "質疑応答14-02",
      "tax_type": "sozoku",
      "size": 1679
    },
    {
      "id": "14-03",
      "title": "遺言書の内容と異なる遺産の分割と贈与税",
      "cite_key": "質疑応答14-03",
      "tax_type": "sozoku",
      "size": 1916
    },
    {
      "id": "14-04",
      "title": "父所有の家屋に子が増築した場合の贈与税の課税関係",
      "cite_key": "質疑応答14-04",
      "tax_type": "sozoku",
      "size": 2081
    },
    {
      "id": "14-05",
      "title": "生命保険契約について契約者変更があった場合",
      "cite_key": "質疑応答14-05",
      "tax_type": "sozoku",
      "size": 2266
    },
    {
      "id": "14-06",
      "title": "医療法人の出資持分の変更があった場合",
      "cite_key": "質疑応答14-06",
      "tax_type": "sozoku",
      "size": 1626
    },
    {
      "id": "14-07",
      "title": "夫婦財産契約と贈与税",
      "cite_key": "質疑応答14-07",
      "tax_type": "sozoku",
      "size": 1714
    },
    {
      "id": "14-08",
      "title": "賃貸アパートの贈与に係る負担付贈与通達の適用関係",
      "cite_key": "質疑応答14-08",
      "tax_type": "sozoku",
      "size": 3119
    },
    {
      "id": "15-01",
      "title": "特定障害者扶養信託契約の「特定障害者の居住の用に供する不動産」の範囲",
      "cite_key": "質疑応答15-01",
      "tax_type": "sozoku",
      "size": 2110
    },
    {
      "id": "15-02",
      "title": "特定障害者扶養信託契約に係る財産を一部払い出し受益者のための居住用不動産を取得することの可否",
      "cite_key": "質疑応答15-02",
      "tax_type": "sozoku",
      "size": 2296
    },
    {
      "id": "15-03",
      "title": "特定障害者扶養信託契約の信託財産の範囲",
      "cite_key": "質疑応答15-03",
      "tax_type": "sozoku",
      "size": 1695
    },
    {
      "id": "15-04",
      "title": "障害者非課税信託申告書を提出した後に特定障害者に該当しないこととなった場合の贈与税の取扱い",
      "cite_key": "質疑応答15-04",
      "tax_type": "sozoku",
      "size": 2041
    },
    {
      "id": "16-01",
      "title": "贈与により取得したものとみなされる保険金で配偶者が居住用不動産を取得した場合の贈与税の配偶者控除",
      "cite_key": "質疑応答16-01",
      "tax_type": "sozoku",
      "size": 1817
    },
    {
      "id": "16-02",
      "title": "贈与を受けた土地の上に他人が建物を建築し、その建物に当該土地の受贈者が居住した場合の贈与税の配偶者控除",
      "cite_key": "質疑応答16-02",
      "tax_type": "sozoku",
      "size": 2261
    },
    {
      "id": "16-03",
      "title": "贈与税の配偶者控除の対象となる居住用不動産の範囲(1)",
      "cite_key": "質疑応答16-03",
      "tax_type": "sozoku",
      "size": 1468
    },
    {
      "id": "16-04",
      "title": "贈与税の配偶者控除の対象となる居住用不動産の範囲(2)",
      "cite_key": "質疑応答16-04",
      "tax_type": "sozoku",
      "size": 1998
    },
    {
      "id": "16-05",
      "title": "日本国籍を有しない者が受ける贈与税の配偶者控除に係る贈与税の申告書の添付書類",
      "cite_key": "質疑応答16-05",
      "tax_type": "sozoku",
      "size": 3392
    },
    {
      "id": "16-06",
      "title": "低額譲受けによる利益相当額についての贈与税の配偶者控除の適用",
      "cite_key": "質疑応答16-06",
      "tax_type": "sozoku",
      "size": 1818
    },
    {
      "id": "16-07",
      "title": "贈与税の配偶者控除の適用を受ける場合における居住用不動産の居住の用に供する時期",
      "cite_key": "質疑応答16-07",
      "tax_type": "sozoku",
      "size": 2217
    },
    {
      "id": "17-01",
      "title": "贈与により取得したものとみなされる生命保険金を住宅取得資金に充てた場合の住宅取得等資金の贈与の特例の適用",
      "cite_key": "質疑応答17-01",
      "tax_type": "sozoku",
      "size": 1751
    },
    {
      "id": "17-02",
      "title": "住宅取得等資金の贈与を受けた者が年の中途で出国した場合の住宅取得等資金の贈与の特例の適用の可否",
      "cite_key": "質疑応答17-02",
      "tax_type": "sozoku",
      "size": 2424
    },
    {
      "id": "17-03",
      "title": "受贈した金銭を一般定期借地権に係る権利金又は保証金に充てた場合の住宅取得等資金の贈与の特例の適用の可否",
      "cite_key": "質疑応答17-03",
      "tax_type": "sozoku",
      "size": 2231
    },
    {
      "id": "17-05",
      "title": "住宅用家屋の新築等の対価又は増改築等の費用の範囲",
      "cite_key": "質疑応答17-05",
      "tax_type": "sozoku",
      "size": 3870
    },
    {
      "id": "17-06",
      "title": "住宅用家屋を新築するための土地の購入資金に充てるために金銭の贈与を受けた場合における住宅取得等資金の贈与の特例の適用の可否",
      "cite_key": "質疑応答17-06",
      "tax_type": "sozoku",
      "size": 2638
    },
    {
      "id": "17-07",
      "title": "店舗兼住宅を取得した場合の床面積要件",
      "cite_key": "質疑応答17-07",
      "tax_type": "sozoku",
      "size": 2505
    },
    {
      "id": "17-08",
      "title": "住宅取得等資金の贈与と住宅借入金等特別控除との関係",
      "cite_key": "質疑応答17-08",
      "tax_type": "sozoku",
      "size": 3228
    },
    {
      "id": "18-01",
      "title": "納税猶予の対象となる農地(2)",
      "cite_key": "質疑応答18-01",
      "tax_type": "sozoku",
      "size": 1793
    },
    {
      "id": "18-02",
      "title": "調整水田に対する納税猶予の適用",
      "cite_key": "質疑応答18-02",
      "tax_type": "sozoku",
      "size": 2024
    },
    {
      "id": "18-03",
      "title": "相続税の納税猶予の適用を受けることができる農業相続人",
      "cite_key": "質疑応答18-03",
      "tax_type": "sozoku",
      "size": 2055
    },
    {
      "id": "18-04",
      "title": "修正申告等による増差税額の納税猶予の適用",
      "cite_key": "質疑応答18-04",
      "tax_type": "sozoku",
      "size": 2031
    },
    {
      "id": "18-05",
      "title": "特例農地等の一部を市に寄附した場合の100分の20の判定",
      "cite_key": "質疑応答18-05",
      "tax_type": "sozoku",
      "size": 1681
    },
    {
      "id": "18-06",
      "title": "特例農地等について農業経営基盤強化促進法第7条第2号に掲げる事業（農地売渡信託等事業）による信託契約を締結した場合の納税猶予期限の確定",
      "cite_key": "質疑応答18-06",
      "tax_type": "sozoku",
      "size": 2119
    },
    {
      "id": "18-07",
      "title": "農業の用に供されていた農地",
      "cite_key": "質疑応答18-07",
      "tax_type": "sozoku",
      "size": 2234
    },
    {
      "id": "18-08",
      "title": "納税猶予の適用を受ける場合の贈与者の農業に従事していた期間",
      "cite_key": "質疑応答18-08",
      "tax_type": "sozoku",
      "size": 1766
    },
    {
      "id": "18-09",
      "title": "納付すべき相続税額が算出されない配偶者についての納税猶予の適用",
      "cite_key": "質疑応答18-09",
      "tax_type": "sozoku",
      "size": 2945
    },
    {
      "id": "18-10",
      "title": "相続税の特例農地等の一部について地役権が設定された場合",
      "cite_key": "質疑応答18-10",
      "tax_type": "sozoku",
      "size": 1317
    },
    {
      "id": "18-11",
      "title": "特例適用農地の譲渡代金の一部について代替農地の取得の見積承認申請があった場合",
      "cite_key": "質疑応答18-11",
      "tax_type": "sozoku",
      "size": 2239
    },
    {
      "id": "18-12",
      "title": "特定農業団体に対し農作業の一部を委託した場合",
      "cite_key": "質疑応答18-12",
      "tax_type": "sozoku",
      "size": 3180
    },
    {
      "id": "18-13",
      "title": "納税猶予の対象となる農地(1)",
      "cite_key": "質疑応答18-13",
      "tax_type": "sozoku",
      "size": 5509
    },
    {
      "id": "18-14",
      "title": "土地区画整理事業に係る土地",
      "cite_key": "質疑応答18-14",
      "tax_type": "sozoku",
      "size": 2001
    },
    {
      "id": "18-15",
      "title": "納税猶予の特例の適用を受けた休耕地をその後転用した場合",
      "cite_key": "質疑応答18-15",
      "tax_type": "sozoku",
      "size": 2167
    },
    {
      "id": "18-16",
      "title": "市民菜園として貸し付けている農地",
      "cite_key": "質疑応答18-16",
      "tax_type": "sozoku",
      "size": 1978
    },
    {
      "id": "18-17",
      "title": "レジャー農園の用に供されている農地",
      "cite_key": "質疑応答18-17",
      "tax_type": "sozoku",
      "size": 1696
    },
    {
      "id": "18-18",
      "title": "修正申告等に係る贈与税（相続税）額の納税猶予に係る加算税",
      "cite_key": "質疑応答18-18",
      "tax_type": "sozoku",
      "size": 1806
    },
    {
      "id": "18-19",
      "title": "農業協同組合の受託経営に係る農地",
      "cite_key": "質疑応答18-19",
      "tax_type": "sozoku",
      "size": 2663
    },
    {
      "id": "18-20",
      "title": "鉄塔の建替え工事のため仮鉄塔の敷地として一時使用されている土地",
      "cite_key": "質疑応答18-20",
      "tax_type": "sozoku",
      "size": 4461
    },
    {
      "id": "18-21",
      "title": "砂利採取中の土地",
      "cite_key": "質疑応答18-21",
      "tax_type": "sozoku",
      "size": 3532
    },
    {
      "id": "18-23",
      "title": "農地所有適格法人に貸し付けることとなった農地",
      "cite_key": "質疑応答18-23",
      "tax_type": "sozoku",
      "size": 1666
    },
    {
      "id": "18-24",
      "title": "同一年中に複数の者に贈与した場合",
      "cite_key": "質疑応答18-24",
      "tax_type": "sozoku",
      "size": 1745
    },
    {
      "id": "18-25",
      "title": "農業所得の申告が贈与者以外の者によって行われていた場合",
      "cite_key": "質疑応答18-25",
      "tax_type": "sozoku",
      "size": 2209
    },
    {
      "id": "18-26",
      "title": "貸付農地がある場合の贈与税の納税猶予の適用",
      "cite_key": "質疑応答18-26",
      "tax_type": "sozoku",
      "size": 1488
    },
    {
      "id": "18-27",
      "title": "同一年中に2人の贈与者から農地等の生前一括贈与を受けた場合",
      "cite_key": "質疑応答18-27",
      "tax_type": "sozoku",
      "size": 2119
    },
    {
      "id": "18-28",
      "title": "2人以上の者が農地等を共有で相続した場合の納税猶予の特例の可否",
      "cite_key": "質疑応答18-28",
      "tax_type": "sozoku",
      "size": 3604
    },
    {
      "id": "18-29",
      "title": "未成年者が農業相続人となった場合の農業所得の申告",
      "cite_key": "質疑応答18-29",
      "tax_type": "sozoku",
      "size": 1979
    },
    {
      "id": "18-30",
      "title": "相続放棄と相続税の納税猶予",
      "cite_key": "質疑応答18-30",
      "tax_type": "sozoku",
      "size": 1789
    },
    {
      "id": "18-31",
      "title": "未成年者が農業相続人となる場合の農業委員会の証明",
      "cite_key": "質疑応答18-31",
      "tax_type": "sozoku",
      "size": 2187
    },
    {
      "id": "18-32",
      "title": "納税猶予の特例の適用を受けている農地等の大半が収用により譲渡されたために農業経営を廃止した場合の利子税の特例",
      "cite_key": "質疑応答18-32",
      "tax_type": "sozoku",
      "size": 2418
    },
    {
      "id": "18-33",
      "title": "仮換地が指定されている相続税の納税猶予の適用を受けている農地等について特定転用を受けた者が、その後の換地処分により清算金の交付を受けた場合の猶予期限の確定処理",
      "cite_key": "質疑応答18-33",
      "tax_type": "sozoku",
      "size": 2481
    },
    {
      "id": "18-34",
      "title": "経営移譲年金の受給資格取得のために経営移譲が行われていた場合の相続税の納税猶予の特例の適用",
      "cite_key": "質疑応答18-34",
      "tax_type": "sozoku",
      "size": 2330
    },
    {
      "id": "18-35",
      "title": "対象年の前年以前又は対象年に農地法第5条の許可を受けた農地等の贈与を行った場合の贈与税の納税猶予の適用",
      "cite_key": "質疑応答18-35",
      "tax_type": "sozoku",
      "size": 3352
    },
    {
      "id": "19-01",
      "title": "共同相続人に該当しない親権者が未成年者である子に代理して遺産分割協議書を作成する場合",
      "cite_key": "質疑応答19-01",
      "tax_type": "sozoku",
      "size": 2797
    },
    {
      "id": "20-01",
      "title": "15年以内の年賦延納をすることができる場合の不動産の占める割合の計算",
      "cite_key": "質疑応答20-01",
      "tax_type": "sozoku",
      "size": 2072
    }
  ]
}
